zmq_tubes-1.16.0.dist-info/METADATA
zmq_tubes-1.16.0.dist-info/WHEEL
zmq_tubes-1.16.0.dist-info/entry_points.txt
zmq_tubes-1.16.0.dist-info/licenses/LICENCE
zmq_tubes/__init__.py
zmq_tubes/manager.py
zmq_tubes/matcher.py
zmq_tubes/monitoring.py
zmq_tubes/threads.py
zmq_tubes-1.16.0.dist-info/RECORD
