Metadata-Version: 2.1
Name: zmq_tubes
Version: 1.16.0
Summary: Wrapper for ZMQ communication.
Keywords: zmq,mqtt,tubes,zmq_tubes
Author-Email: Martin Korbel <mkorbel@alps.cz>
License: MIT
Classifier: Topic :: System :: Networking
Classifier: Topic :: Software Development :: Libraries :: Python Modules
Project-URL: homepage, https://github.com/calcite/zmq_tubes
Project-URL: repository, https://github.com/calcite/zmq_tubes
Project-URL: documentation, https://github.com/calcite/zmq_tubes
Requires-Python: <4.0,>=3.9
Requires-Dist: pyzmq
Provides-Extra: dev
Requires-Dist: pytest>=6.2.5; extra == "dev"
Requires-Dist: PyYAML<7.0,>=5.4.1; extra == "dev"
Requires-Dist: pytest-asyncio; extra == "dev"
